address_book_for_IVT2023/__init__.py
address_book_for_IVT2023/app.py
address_book_for_IVT2023/controllers.py
address_book_for_IVT2023/models.py
address_book_for_IVT2023/views.py
address_book_for_IVT2023-0.1.dist-info/METADATA
address_book_for_IVT2023-0.1.dist-info/WHEEL
address_book_for_IVT2023-0.1.dist-info/top_level.txt
address_book_for_IVT2023-0.1.dist-info/RECORD
