Metadata-Version: 2.1
Name: address-book-for-IVT2023
Version: 0.1
Summary: address book
Home-page: http://example.com
Author: P_Ihor
Author-email: igoamigo2000@gmail.com
License: MIT
Platform: UNKNOWN
Classifier: Development Status :: 3 - Alpha
Classifier: License :: OSI Approved :: MIT License
Classifier: Programming Language :: Python :: 3.1
Classifier: Topic :: Text Processing :: Linguistic
Requires-Dist: Jinja2 (==2.11.2)
Requires-Dist: MarkupSafe (==1.1.1)
Requires-Dist: SQLAlchemy (==1.3.19)
